{
  "ref": "def_3_18",
  "kind": "def",
  "section": "3.3",
  "title": "ISigmaSeparation",
  "type": "definition",
  "status": {
    "formalized": "yes",
    "proven": "n/a",
    "solved": "yes"
  },
  "tex_block_html": "<p>Let $G=(J,V,E,L)$ be a CDMG and $A,B,C \\ins J \\cup V$ (not necessarily disjoint) subset of nodes.\n    We then say that:</p>\n<ol class=\"enum\"><li><em>$A$ is $i\\sigma$-separated from $B$ given $C$ in $G$</em>, in symbols:\n    \\[ A \\isPerp_G B \\given C, \\]\n    if every walk from a node in $A$ to a node in $J \\cup B$ (sic!) is $\\sigma$-blocked by $C$.</li><li>If that property does not hold we will write:\n            \\[ A \\nisPerp_G B \\given C. \\]</li><li>We also define the special case:\n                \\[ A \\isPerp_G B \\qquad :\\iff \\qquad A \\isPerp_G B \\given \\emptyset.\\]</li><li>For the special case $J = \\emptyset$—that is, if $G$ has no input nodes—$i\\sigma$-separation is also called <em>$\\sigma$-separation</em>, and we write:\n          \\[A \\sPerp_G B \\given C := A \\isPerp_G B \\given C, \\qquad A \\nsPerp_G B \\given C := A \\nisPerp_G B \\given C.\\]\n<p>Note that $\\sigma$-separation is symmetric: $A \\sPerp_G B \\given C \\iff B \\sPerp_G A \\given C$, since when $J = \\emptyset$ the set of walks between $A$ and $B$ is the same regardless of direction, and the $\\sigma$-blocking conditions are invariant under walk reversal.</li></ol></p>",
  "tex_statement": {
    "raw": "% Definition file for row def_3_18 -- \"ISigmaSeparation\".\n% Auto-generated stub by scaffold/solve_chapter.py at row start. The\n% manager agent (or a worker dispatched by it) fills the body below with the\n% Lean-faithful definition statement(s). Stays close to the lecture notes.\n%\n% This file is a sibling of `main.tex` inside `<subsection>/tex/`. The\n% `subfiles` package lets it compile both standalone (resolving its\n% preamble via `main.tex`) and as part of `main.tex` via `\\subfile{...}`.\n\n\\documentclass[main]{subfiles}\n\n\\begin{document}\n% ref: def_3_18\n% title: ISigmaSeparation\n\\def\\rowref{def\\_3\\_18}\n\\phantomsection\\label{def_3_18}\n\n\\begin{Def}[$i\\sigma$-separation]\\label{def:sigma_separation}\n    Let $G = (J, V, E, L)$ be a CDMG (def \\ref{def-cdmg}); throughout we use the notation of def \\ref{not-cdmg}, the walk definition of def \\ref{def:walks}, item~i., and the $\\sigma$-blocking predicate ``$\\pi$ is $C$-$\\sigma$-blocked'' (equivalently ``$\\sigma$-blocked given $C$'') of def \\ref{def:sigma_blocking}. Let $A, B, C \\ins J \\cup V$ be subsets of nodes; $A$, $B$, $C$ are \\emph{not} assumed to be pairwise disjoint, nor disjoint from the input-node set $J$, nor non-empty.\n\n    We then say that:\n    \\begin{enumerate}\n        \\item \\emph{$A$ is $i\\sigma$-separated from $B$ given $C$ in $G$,} in symbols\n            \\[\n                A \\isPerp_G B \\given C,\n            \\]\n            iff: for every integer $n \\ge 0$ and every walk\n            \\[\n                \\pi = (v_0, a_0, v_1, a_1, \\dots, v_{n-1}, a_{n-1}, v_n)\n            \\]\n            in $G$ (def \\ref{def:walks}, item~i.) with $v_0 \\in A$ and $v_n \\in J \\cup B$\\footnote{The choice to include $J$ here in this place is non-standard in the literature. However, if we include $J$ in this definition here the implied (asymmetric) separoid rules for $id$-/$i\\sigma$-separation will be of the same form as those for Markov kernels regarding conditional independence. This is the reason we include $J$ here.\\label{fn:why-J}}, the walk $\\pi$ is $C$-$\\sigma$-blocked in the sense of def \\ref{def:sigma_blocking}.\n\n            \\emph{Range of the walk quantifier.} The universal quantifier ranges over \\emph{all} walks of every admissible length $n \\ge 0$, including the trivial (length-zero) walk: whenever there exists $a \\in A \\cap (J \\cup B)$, the tuple $\\pi = (a)$ is, by def \\ref{def:walks}, item~i.\\ (case $n = 0$), a walk from $a$ to $a$ in $G$ with $v_0 = v_n = a$, hence $v_0 \\in A$ and $v_n \\in J \\cup B$, and is therefore in the scope of the quantifier. Whether such a trivial walk is $C$-$\\sigma$-blocked is determined by applying def \\ref{def:sigma_blocking} at $n = 0$ (the blocking status reduces to: is the single end-position $k = 0$ a blockable non-collider with $v_0 \\in C$, in the sense of def \\ref{def:unblockable_noncollider}? --- which is the formalizer's downstream derivation, not part of the literal definition stated here). In particular, the condition is \\emph{not} vacuously satisfied when $A \\cap (J \\cup B)$ is non-empty, and downstream consumers should not assume otherwise.\n\n            \\emph{Asymmetric inclusion of $J$ on the right.} The right-hand endpoint constraint $v_n \\in J \\cup B$ (rather than $v_n \\in B$) is the deliberate, non-standard choice flagged in footnote~\\ref{fn:why-J} of the LN: with $J$ included on the right, the implied (asymmetric) separoid rules for $i\\sigma$-separation match the corresponding rules for conditional independence under Markov kernels. As a direct consequence, the marginal case $B = \\emptyset$ is \\emph{not} vacuous: $A \\isPerp_G \\emptyset \\given C$ asserts that every walk in $G$ from a node in $A$ to a node in $J$ is $C$-$\\sigma$-blocked, which is a genuine condition whenever $J \\neq \\emptyset$. Only when $J = \\emptyset$ does $A \\isPerp_G \\emptyset \\given C$ recover the usual ``separation from the empty set is vacuous'' reading.\n\n        \\item \\emph{If the property in item~1 does not hold} --- equivalently, if there exist an integer $n \\ge 0$ and a walk\n            \\[\n                \\pi = (v_0, a_0, v_1, \\dots, a_{n-1}, v_n)\n            \\]\n            in $G$ with $v_0 \\in A$, $v_n \\in J \\cup B$, and $\\pi$ is \\emph{not} $C$-$\\sigma$-blocked (equivalently, $\\pi$ is $C$-$\\sigma$-open in the sense of def \\ref{def:sigma_blocking}) --- we write\n            \\[\n                A \\nisPerp_G B \\given C.\n            \\]\n\n        \\item The unconditional ($C = \\emptyset$) special case is defined as the abbreviation\n            \\[\n                A \\isPerp_G B \\quad :\\iff \\quad A \\isPerp_G B \\given \\emptyset.\n            \\]\n            Unfolded via item~1: $A \\isPerp_G B$ iff for every $n \\ge 0$ and every walk $\\pi$ in $G$ from a node $v_0 \\in A$ to a node $v_n \\in J \\cup B$, $\\pi$ is $\\emptyset$-$\\sigma$-blocked in the sense of def \\ref{def:sigma_blocking}.\n\n        \\item For the special case $J = \\emptyset$ --- that is, $G$ has no input nodes --- $i\\sigma$-separation is also called \\emph{$\\sigma$-separation}, and we write\n            \\[\n                A \\sPerp_G B \\given C \\;\\; := \\;\\; A \\isPerp_G B \\given C,\n                \\qquad\n                A \\nsPerp_G B \\given C \\;\\; := \\;\\; A \\nisPerp_G B \\given C.\n            \\]\n            Under $J = \\emptyset$ the right-hand endpoint constraint $v_n \\in J \\cup B$ reduces to $v_n \\in B$, so $A \\sPerp_G B \\given C$ unfolds to: for every $n \\ge 0$ and every walk $\\pi$ in $G$ from a node $v_0 \\in A$ to a node $v_n \\in B$, $\\pi$ is $C$-$\\sigma$-blocked in the sense of def \\ref{def:sigma_blocking}.\n    \\end{enumerate}\n\n    \\emph{Treatment of the trailing LN remark.}\n    The LN source block (\\texttt{graphs.tex}, \\texttt{\\textbackslash label\\{def:sigma\\_separation\\}}) closes item~4 with an embedded \\texttt{claimmark} stating that $\\sigma$-separation is symmetric ($A \\sPerp_G B \\given C \\iff B \\sPerp_G A \\given C$ when $J = \\emptyset$), justified informally by the observation that walks ``between $A$ and $B$'' are the same regardless of direction and that the $\\sigma$-blocking conditions are invariant under walk reversal. Per the convention adopted in the sibling row \\texttt{def\\_3\\_17} (whose embedded \\texttt{claimmark} for \\texttt{claim\\_3\\_21} is treated identically), that informal pre-statement is \\emph{intentionally excluded} from the formalization of def \\ref{def:sigma_separation}: it is not part of the definition proper, and its substantive content is the dedicated separate claim row \\texttt{claim\\_3\\_22} (\\emph{$\\sigma$-separation is symmetric}), whose statement and proof live in \\texttt{claim\\_3\\_22\\_statement\\_SigmaSeparationSymmetric.tex} and \\texttt{claim\\_3\\_22\\_proof\\_SigmaSeparationSymmetric.tex} respectively. The row's authoritative \\texttt{addition\\_to\\_the\\_LN} clause \\texttt{[sigma\\_symmetry\\_claim\\_invokes\\_unstated\\_reversal\\_invariance]} records (as background, not as a Lean obligation within this definition) the precise sense in which the informal justification is to be read: in a CDMG, a walk per def \\ref{def:walks}, item~i.\\ is a sequence of incident edges \\emph{without regard to traversal orientation}, so reading the tuple in reverse yields another walk with start- and end-nodes swapped; this walk-reversal map is an involution on the set of walks in $G$. Symmetry of $\\sigma$-separation (when $J = \\emptyset$) is to be understood as resting on this involution together with the fact that the $\\sigma$-blocking conditions of def \\ref{def:sigma_blocking} on internal positions are stated invariantly under walk reversal --- but this reasoning is the content of the proof of \\texttt{claim\\_3\\_22}, not of the present definition. No Lean obligation is to be derived from the embedded \\texttt{claimmark} within this definition.\n\\end{Def}\n\n\\end{document}\n",
    "html": "<p>Let $G = (J, V, E, L)$ be a CDMG (def <a href=\"#def_3_1\" class=\"refrow\"><code>def-cdmg</code></a>); throughout we use the notation of def <a href=\"#def_3_2\" class=\"refrow\"><code>not-cdmg</code></a>, the walk definition of def <a href=\"#def_3_4\" class=\"refrow\"><code>def:walks</code></a>, item&nbsp;i., and the $\\sigma$-blocking predicate “$\\pi$ is $C$-$\\sigma$-blocked” (equivalently “$\\sigma$-blocked given $C$”) of def <a href=\"#def_3_17\" class=\"refrow\"><code>def:sigma_blocking</code></a>. Let $A, B, C \\ins J \\cup V$ be subsets of nodes; $A$, $B$, $C$ are <em>not</em> assumed to be pairwise disjoint, nor disjoint from the input-node set $J$, nor non-empty.</p>\n<p>We then say that:</p>\n<ol class=\"enum\"><li><em>$A$ is $i\\sigma$-separated from $B$ given $C$ in $G$,</em> in symbols\n            \\[\n                A \\isPerp_G B \\given C,\n            \\]\n            iff: for every integer $n \\ge 0$ and every walk\n            \\[\n                \\pi = (v_0, a_0, v_1, a_1, \\dots, v_{n-1}, a_{n-1}, v_n)\n            \\]\n            in $G$ (def <a href=\"#def_3_4\" class=\"refrow\"><code>def:walks</code></a>, item&nbsp;i.) with $v_0 \\in A$ and $v_n \\in J \\cup B$, the walk $\\pi$ is $C$-$\\sigma$-blocked in the sense of def <a href=\"#def_3_17\" class=\"refrow\"><code>def:sigma_blocking</code></a>.\n<p><em>Range of the walk quantifier.</em> The universal quantifier ranges over <em>all</em> walks of every admissible length $n \\ge 0$, including the trivial (length-zero) walk: whenever there exists $a \\in A \\cap (J \\cup B)$, the tuple $\\pi = (a)$ is, by def <a href=\"#def_3_4\" class=\"refrow\"><code>def:walks</code></a>, item&nbsp;i.\\ (case $n = 0$), a walk from $a$ to $a$ in $G$ with $v_0 = v_n = a$, hence $v_0 \\in A$ and $v_n \\in J \\cup B$, and is therefore in the scope of the quantifier. Whether such a trivial walk is $C$-$\\sigma$-blocked is determined by applying def <a href=\"#def_3_17\" class=\"refrow\"><code>def:sigma_blocking</code></a> at $n = 0$ (the blocking status reduces to: is the single end-position $k = 0$ a blockable non-collider with $v_0 \\in C$, in the sense of def <a href=\"#def_3_16\" class=\"refrow\"><code>def:unblockable_noncollider</code></a>? — which is the formalizer's downstream derivation, not part of the literal definition stated here). In particular, the condition is <em>not</em> vacuously satisfied when $A \\cap (J \\cup B)$ is non-empty, and downstream consumers should not assume otherwise.</p>\n<p><em>Asymmetric inclusion of $J$ on the right.</em> The right-hand endpoint constraint $v_n \\in J \\cup B$ (rather than $v_n \\in B$) is the deliberate, non-standard choice flagged in footnote&nbsp;<a href=\"#def_3_18\" class=\"refrow\"><code>fn:why-J</code></a> of the LN: with $J$ included on the right, the implied (asymmetric) separoid rules for $i\\sigma$-separation match the corresponding rules for conditional independence under Markov kernels. As a direct consequence, the marginal case $B = \\emptyset$ is <em>not</em> vacuous: $A \\isPerp_G \\emptyset \\given C$ asserts that every walk in $G$ from a node in $A$ to a node in $J$ is $C$-$\\sigma$-blocked, which is a genuine condition whenever $J \\neq \\emptyset$. Only when $J = \\emptyset$ does $A \\isPerp_G \\emptyset \\given C$ recover the usual “separation from the empty set is vacuous” reading.</li><li><em>If the property in item&nbsp;1 does not hold</em> — equivalently, if there exist an integer $n \\ge 0$ and a walk\n            \\[\n                \\pi = (v_0, a_0, v_1, \\dots, a_{n-1}, v_n)\n            \\]\n            in $G$ with $v_0 \\in A$, $v_n \\in J \\cup B$, and $\\pi$ is <em>not</em> $C$-$\\sigma$-blocked (equivalently, $\\pi$ is $C$-$\\sigma$-open in the sense of def <a href=\"#def_3_17\" class=\"refrow\"><code>def:sigma_blocking</code></a>) — we write\n            \\[\n                A \\nisPerp_G B \\given C.\n            \\]</li><li>The unconditional ($C = \\emptyset$) special case is defined as the abbreviation\n            \\[\n                A \\isPerp_G B \\quad :\\iff \\quad A \\isPerp_G B \\given \\emptyset.\n            \\]\n            Unfolded via item&nbsp;1: $A \\isPerp_G B$ iff for every $n \\ge 0$ and every walk $\\pi$ in $G$ from a node $v_0 \\in A$ to a node $v_n \\in J \\cup B$, $\\pi$ is $\\emptyset$-$\\sigma$-blocked in the sense of def <a href=\"#def_3_17\" class=\"refrow\"><code>def:sigma_blocking</code></a>.</li><li>For the special case $J = \\emptyset$ — that is, $G$ has no input nodes — $i\\sigma$-separation is also called <em>$\\sigma$-separation</em>, and we write\n            \\[\n                A \\sPerp_G B \\given C \\;\\; := \\;\\; A \\isPerp_G B \\given C,\n                \\qquad\n                A \\nsPerp_G B \\given C \\;\\; := \\;\\; A \\nisPerp_G B \\given C.\n            \\]\n            Under $J = \\emptyset$ the right-hand endpoint constraint $v_n \\in J \\cup B$ reduces to $v_n \\in B$, so $A \\sPerp_G B \\given C$ unfolds to: for every $n \\ge 0$ and every walk $\\pi$ in $G$ from a node $v_0 \\in A$ to a node $v_n \\in B$, $\\pi$ is $C$-$\\sigma$-blocked in the sense of def <a href=\"#def_3_17\" class=\"refrow\"><code>def:sigma_blocking</code></a>.</li></ol></p>\n<p><em>Treatment of the trailing LN remark.</em>\n    The LN source block (<code>graphs.tex</code>, \\texttt{\\label\\{def:sigma\\_separation\\}}) closes item&nbsp;4 with an embedded <code>claimmark</code> stating that $\\sigma$-separation is symmetric ($A \\sPerp_G B \\given C \\iff B \\sPerp_G A \\given C$ when $J = \\emptyset$), justified informally by the observation that walks “between $A$ and $B$” are the same regardless of direction and that the $\\sigma$-blocking conditions are invariant under walk reversal. Per the convention adopted in the sibling row <code>def_3_17</code> (whose embedded <code>claimmark</code> for <code>claim_3_21</code> is treated identically), that informal pre-statement is <em>intentionally excluded</em> from the formalization of def <a href=\"#def_3_18\" class=\"refrow\"><code>def:sigma_separation</code></a>: it is not part of the definition proper, and its substantive content is the dedicated separate claim row <code>claim_3_22</code> (<em>$\\sigma$-separation is symmetric</em>), whose statement and proof live in <code>claim_3_22_statement_SigmaSeparationSymmetric.tex</code> and <code>claim_3_22_proof_SigmaSeparationSymmetric.tex</code> respectively. The row's authoritative <code>addition_to_the_LN</code> clause <code>[sigma_symmetry_claim_invokes_unstated_reversal_invariance]</code> records (as background, not as a Lean obligation within this definition) the precise sense in which the informal justification is to be read: in a CDMG, a walk per def <a href=\"#def_3_4\" class=\"refrow\"><code>def:walks</code></a>, item&nbsp;i.\\ is a sequence of incident edges <em>without regard to traversal orientation</em>, so reading the tuple in reverse yields another walk with start- and end-nodes swapped; this walk-reversal map is an involution on the set of walks in $G$. Symmetry of $\\sigma$-separation (when $J = \\emptyset$) is to be understood as resting on this involution together with the fact that the $\\sigma$-blocking conditions of def <a href=\"#def_3_17\" class=\"refrow\"><code>def:sigma_blocking</code></a> on internal positions are stated invariantly under walk reversal — but this reasoning is the content of the proof of <code>claim_3_22</code>, not of the present definition. No Lean obligation is to be derived from the embedded <code>claimmark</code> within this definition.</p>",
    "env": "Def",
    "env_title": "$i\\sigma$-separation",
    "source_path": "leanification/Chapter3_GraphTheory/Section3_3/tex/def_3_18_ISigmaSeparation.tex"
  },
  "tex_proof": null,
  "lean_blocks": [
    {
      "kind": "helper",
      "code": "variable {Node : Type*} [DecidableEq Node]",
      "explanation": "This is a `variable` declaration: Lean auto-binds `Node : Type*` and the instance `[DecidableEq Node]` as implicit arguments to every subsequent declaration in the surrounding `CDMG` namespace, sparing us from rewriting the same parameters on `IsISigmaSeparated` and its four notational siblings. The `Type*` notation makes `Node` universe-polymorphic, so callers can instantiate it at any universe level. The `DecidableEq Node` assumption is load-bearing because the ambient `CDMG Node` structure stores `J, V : Finset Node` and `E, L : Finset (Node × Node)`; decidable equality is what lets those `Finset`s exist and what enables the `(G.J : Set Node)` coercion appearing in the main predicate. Stronger structure on `Node` (e.g. `Fintype`, `LinearOrder`) is not required here and is deferred to downstream consumers that actually use it. Same convention as the rest of `Chapter3_GraphTheory`'s files.",
      "code_annotated": "-- Auto-binds `Node` + `DecidableEq Node` as implicits; decidability backs `CDMG`'s `Finset` fields and the `G.J` coercion below.\nvariable {Node : Type*} [DecidableEq Node]"
    },
    {
      "kind": "main",
      "code": "def IsISigmaSeparated (G : CDMG Node) (A B C : Set Node)\n    (hA : A ⊆ ↑G.J ∪ ↑G.V) (hB : B ⊆ ↑G.J ∪ ↑G.V) (hC : C ⊆ ↑G.J ∪ ↑G.V) : Prop :=\n  ∀ {u v : Node} (π : Walk G u v),\n      u ∈ A → v ∈ (G.J : Set Node) ∪ B → π.IsSigmaBlockedGiven C hC",
      "explanation": "This block introduces `G.IsISigmaSeparated A B C hA hB hC` — the LN's `A ⫫ⁱˢ_G B | C` — as the kernel of the $\\sigma$-separation framework. The body is the LN's universal over walks, spelled word-for-word: every walk `π : Walk G u v` with `u ∈ A` and right endpoint `v ∈ J ∪ B` is $C$-$\\sigma$-blocked in the sense of `def_3_17`. The walk binds `{u v}` implicitly so endpoints are inferred from the walk's type, mirroring `def_3_16`'s `IsBlockableNonCollider` binder shape. The right endpoint is `(G.J : Set Node) ∪ B`: `G.J : Finset Node` and `B : Set Node` are heterogeneous, so the `Set`-level coercion is the only well-typed move and lifts every `Set.mem_union` lemma directly. The three subset premises pin \"$A, B, C \\subseteq J \\cup V$\" at the type-signature level; only `hC` is consumed (threaded into `π.IsSigmaBlockedGiven C hC`), so the `set_option linter.unusedVariables false in` prefix is needed for `hA` / `hB`. Items 2–5 of the row (negation, unconditional `C = ∅` shorthand, $J = ∅$ $\\sigma$-name aliases) all forward to this predicate.",
      "code_annotated": "-- LN `A ⫫ⁱˢ_G B | C` (item 1); kernel that items 2-5 forward to. Subset premises pin `A,B,C ⊆ J ∪ V`; only `hC` is consumed in the body.\nset_option linter.unusedVariables false in\ndef IsISigmaSeparated (G : CDMG Node) (A B C : Set Node)\n    -- Three explicit per-set subset hypotheses match the LN's \"A, B, C ⊆ J ∪ V\" verbatim and close the silent-admission leak at the def site.\n    (hA : A ⊆ ↑G.J ∪ ↑G.V) (hB : B ⊆ ↑G.J ∪ ↑G.V) (hC : C ⊆ ↑G.J ∪ ↑G.V) : Prop :=\n  -- Walk-first universal: `{u v}` implicit endpoints are inferred from `Walk G u v`; reads as the LN's \"for every walk π\".\n  ∀ {u v : Node} (π : Walk G u v),\n      -- LN's asymmetric J on the right; `(G.J : Set Node)` coerces the `Finset` so the set-union with `B : Set Node` typechecks. Forwards `hC` to `def_3_17`'s blocked-walk predicate.\n      u ∈ A → v ∈ (G.J : Set Node) ∪ B → π.IsSigmaBlockedGiven C hC"
    },
    {
      "kind": "main",
      "code": "def IsNotISigmaSeparated (G : CDMG Node) (A B C : Set Node)\n    (hA : A ⊆ ↑G.J ∪ ↑G.V) (hB : B ⊆ ↑G.J ∪ ↑G.V) (hC : C ⊆ ↑G.J ∪ ↑G.V) : Prop :=\n  ¬ G.IsISigmaSeparated A B C hA hB hC",
      "explanation": "This block introduces `G.IsNotISigmaSeparated A B C` — the LN's `A ⪥ⁱˢ_G B | C` — as a named alias for `¬ G.IsISigmaSeparated A B C`. The same three domain premises `hA`, `hB`, `hC` ride along on the signature so that interchange with the underlying predicate is type-compatible without bridging adapters. The body is a single `¬`, which makes the unfolding `G.IsNotISigmaSeparated A B C hA hB hC = ¬ G.IsISigmaSeparated A B C hA hB hC` hold by `rfl`: any proof that needs to switch between the named negation and the unfolded universal can do so with `unfold IsNotISigmaSeparated` or `simp only [IsNotISigmaSeparated]`, never a classical equivalence lemma. The named-`def` shape is preferred over inlining `¬ IsISigmaSeparated` at every downstream call site because the LN itself introduces `\\nisPerp` as named notation; mirroring that with a Lean alias keeps the LN-to-Lean grep one-to-one. The tex's ``equivalently, ∃ walk … not $C$-$\\sigma$-blocked'' reformulation is the classical De Morgan dual of the negated universal — a one-line lemma when needed, not a parallel positive-existential definition (which would sever the definitional link with `IsISigmaSeparated`).",
      "code_annotated": "-- Named negation `A ⪥ⁱˢ_G B | C`; `rfl`-equal to `¬ IsISigmaSeparated`, no classical bridge needed.\ndef IsNotISigmaSeparated (G : CDMG Node) (A B C : Set Node)\n    -- Same three domain premises as the underlying predicate so the signatures stay parallel at call sites.\n    (hA : A ⊆ ↑G.J ∪ ↑G.V) (hB : B ⊆ ↑G.J ∪ ↑G.V) (hC : C ⊆ ↑G.J ∪ ↑G.V) : Prop :=\n  -- Body forwards to the negation of the iσ predicate, with all six arguments passed through unchanged.\n  ¬ G.IsISigmaSeparated A B C hA hB hC"
    },
    {
      "kind": "main",
      "code": "abbrev IsISigmaSeparatedEmpty (G : CDMG Node) (A B : Set Node)\n    (hA : A ⊆ ↑G.J ∪ ↑G.V) (hB : B ⊆ ↑G.J ∪ ↑G.V) : Prop :=\n  G.IsISigmaSeparated A B ∅ hA hB (Set.empty_subset _)",
      "explanation": "This block introduces the LN's unconditional shorthand `A ⫫ⁱˢ_G B := A ⫫ⁱˢ_G B | ∅` as `G.IsISigmaSeparatedEmpty A B`. The third subset hypothesis is dropped from the call-site signature because it would be the constant `Set.empty_subset _`; supplying it inline keeps the call site to two arguments `(hA hB)`, matching the LN's notation which mentions only `A` and `B`. The use of `abbrev` rather than `def` is load-bearing for ergonomics: `abbrev` is reducibly transparent, so `G.IsISigmaSeparatedEmpty A B hA hB` unfolds to `G.IsISigmaSeparated A B ∅ hA hB (Set.empty_subset _)` at every elaboration site without any explicit `unfold` step. Every lemma about `IsISigmaSeparated` fires automatically on the shorthand and vice versa. A `def` here would create an opaque alias and force `unfold IsISigmaSeparatedEmpty` at every interchange, which the LN's ``is defined as'' reading does not justify. No separate negated counterpart exists at this level — downstream sites needing ``not unconditionally $i\\sigma$-separated'' spell it as `¬ G.IsISigmaSeparatedEmpty A B hA hB` or as `G.IsNotISigmaSeparated A B ∅ hA hB (Set.empty_subset _)`, and the `abbrev`'s transparency makes the two interchangeable.",
      "code_annotated": "-- Unconditional shorthand `A ⫫ⁱˢ_G B`; `abbrev` (not `def`) so it reduces to the underlying predicate at every elaboration site.\nabbrev IsISigmaSeparatedEmpty (G : CDMG Node) (A B : Set Node)\n    -- Two premises only; the third `hC : ∅ ⊆ _` is supplied inline via `Set.empty_subset _` and not exposed at the call site.\n    (hA : A ⊆ ↑G.J ∪ ↑G.V) (hB : B ⊆ ↑G.J ∪ ↑G.V) : Prop :=\n  -- Specialise `IsISigmaSeparated` at `C = ∅`; the `Set.empty_subset _` term discharges the missing third hypothesis.\n  G.IsISigmaSeparated A B ∅ hA hB (Set.empty_subset _)"
    },
    {
      "kind": "main",
      "code": "def IsSigmaSeparated (G : CDMG Node) (hJ : G.J = ∅) (A B C : Set Node)\n    (hA : A ⊆ ↑G.J ∪ ↑G.V) (hB : B ⊆ ↑G.J ∪ ↑G.V) (hC : C ⊆ ↑G.J ∪ ↑G.V) : Prop :=\n  G.IsISigmaSeparated A B C hA hB hC",
      "explanation": "This block introduces the LN's $\\sigma$-separation predicate `G.IsSigmaSeparated hJ A B C` — written `A ⫫_G B | C` in the LN — as the renaming of $i\\sigma$-separation for the special case `G.J = ∅`. The premise `hJ : G.J = ∅` enters the signature explicitly: it is the LN's typed-concept distinction between $\\sigma$-separation (only available when the input-node set is empty) and $i\\sigma$-separation (the general case). The body is a transparent forward to `IsISigmaSeparated`: under `G.J = ∅` the right-endpoint constraint `v ∈ (G.J : Set Node) ∪ B` reduces to `v ∈ B`, but that reduction is a consequence of `hJ` consumed at call sites, not a rewrite baked into the body. The encoding is `def`, not `abbrev`, precisely because `hJ` is a dependent hypothesis: an `abbrev` would unfold eagerly and `hJ` would vanish from goal displays at unrelated tactic steps, erasing the $\\sigma$-vs-$i\\sigma$ symbolic distinction the LN takes care to maintain. The three domain premises `hA`, `hB`, `hC` are the same as on `IsISigmaSeparated`; the body forwards them unchanged. Downstream consumers such as the $\\sigma$-separation symmetry claim, and the chapter-4 Markov-property results, name the predicate via `IsSigmaSeparated` whenever they reason under `G.J = ∅`.",
      "code_annotated": "-- `\\sigma`-separation `A ⫫_G B | C`; the LN reserves this name for the `G.J = ∅` specialisation of `i\\sigma`-separation.\ndef IsSigmaSeparated (G : CDMG Node) (hJ : G.J = ∅) (A B C : Set Node)\n    -- Same `A, B, C ⊆ J ∪ V` domain premises as the underlying iσ predicate; the renaming does not loosen the domain.\n    (hA : A ⊆ ↑G.J ∪ ↑G.V) (hB : B ⊆ ↑G.J ∪ ↑G.V) (hC : C ⊆ ↑G.J ∪ ↑G.V) : Prop :=\n  -- Body forwards verbatim to `IsISigmaSeparated`; `hJ` is carried on the signature for LN-faithfulness, not consumed here.\n  G.IsISigmaSeparated A B C hA hB hC"
    },
    {
      "kind": "main",
      "code": "def IsNotSigmaSeparated (G : CDMG Node) (hJ : G.J = ∅) (A B C : Set Node)\n    (hA : A ⊆ ↑G.J ∪ ↑G.V) (hB : B ⊆ ↑G.J ∪ ↑G.V) (hC : C ⊆ ↑G.J ∪ ↑G.V) : Prop :=\n  G.IsNotISigmaSeparated A B C hA hB hC",
      "explanation": "This block introduces the LN's `A ⪥_G B | C` — ``not $\\sigma$-separated'' — as `G.IsNotSigmaSeparated hJ A B C`, the paired negated notation under `G.J = ∅`. The LN introduces `\\nsPerp` and `\\sPerp` together in item 4, and downstream sites use the two together (claim statements and proof case-splits alternate between $\\sigma$-separated and not-$\\sigma$-separated), so this declaration mirrors `IsSigmaSeparated`'s signature exactly: the same `(hJ : G.J = ∅)` premise, the same three domain premises `hA`, `hB`, `hC`, the same `def`-not-`abbrev` encoding for the same reason (`hJ` is a dependent hypothesis whose visibility would be lost under `abbrev`-grade reducibility). The body forwards directly to `IsNotISigmaSeparated`; the negated content is not re-derived here. In particular, this declaration does *not* re-introduce a positive-existential reformulation of the negation — the existential dual remains the classical De Morgan lemma noted on `IsNotISigmaSeparated`, shared across both the $i\\sigma$ and $\\sigma$ names. Together with the preceding four declarations, this completes the LN's four-item separation block as five named, signature-aligned Lean predicates.",
      "code_annotated": "-- `\\sigma`-not-separation `A ⪥_G B | C`; the paired negated alias of `IsSigmaSeparated` under `G.J = ∅`.\ndef IsNotSigmaSeparated (G : CDMG Node) (hJ : G.J = ∅) (A B C : Set Node)\n    -- Identical domain premises to the positive `IsSigmaSeparated`; pair is introduced and used as a unit downstream.\n    (hA : A ⊆ ↑G.J ∪ ↑G.V) (hB : B ⊆ ↑G.J ∪ ↑G.V) (hC : C ⊆ ↑G.J ∪ ↑G.V) : Prop :=\n  -- Body forwards to the named iσ negation; no new content beyond the σ-rename.\n  G.IsNotISigmaSeparated A B C hA hB hC"
    }
  ],
  "lean_source_url": "https://github.com/schipeltaper/causality-leanified/blob/main/leanification/Chapter3_GraphTheory/Section3_3/ISigmaSeparation.lean",
  "lean_file_path": "leanification/Chapter3_GraphTheory/Section3_3/ISigmaSeparation.lean",
  "addition_to_the_LN": "[sigma_symmetry_claim_invokes_unstated_reversal_invariance] In a CDMG, a walk is a sequence of incident edges without regard to edge orientation; consequently, every walk from $A$ to $B$ is, read in reverse, a walk from $B$ to $A$, and this reversal is an involution on the set of walks. The symmetry of $\\sigma$-separation (when $J = \\emptyset$) is to be understood as resting on this walk-reversal involution together with the fact that the $\\sigma$-blocking conditions on internal nodes are stated in a manner invariant under reversal.",
  "design_choices": "**Asymmetric `J`-inclusion on the right, spelled `v ∈ (G.J : Set Node) ∪ B`.** Per LN footnote `fn:why-J` of `graphs.tex \\label{def:sigma_separation}`: including `J` on the right makes the implied separoid rules for `id`/`iσ`-separation match Markov-kernel conditional independence — payload-bearing for the \"J-Inverted Right Decomposition\" axiom in `scms4.tex`. Corollary `empty_b_non_vacuous_when_j_nonempty`: `G.IsISigmaSeparated A ∅ C` is not vacuous when `G.J ≠ ∅` — it asserts every walk from `A` into `J` is `C`-σ-blocked. Only at `J = ∅` (item 4's σ-rename, gated by `hJ : G.J = ∅`) does the constraint collapse to `v ∈ B`. The coercion is forced: `G.J : Finset Node` and `B : Set Node` are heterogeneous and only the set-level union typechecks.\n\n**Flat `∀`-over-walks shape, not a quotient by reversal-classes.** An alternative — universal over reversal-equivalence classes under the involution flagged by `[sigma_symmetry_claim_invokes_unstated_reversal_invariance]` — is rejected on three grounds: (a) the addition is background for `claim_3_22` (`SigmaSeparationSymmetric`), whose proof transports across the involution given the flat shape; (b) every downstream `A ⊥^iσ B | C` consumer (chapter 4+ Markov-property, do-calculus, iSCM identification, σ-independence-model / causal-relations / minimal-separating-sets) pattern-matches on the flat shape, so a quotient encoding would force `Quot.mk` / `Quot.lift` dispatch and scramble the 1-to-1 LN-to-Lean correspondence; (c) the asymmetric `J`-inclusion would be lost under reversal-class collapse, since reversal swaps endpoints but `J` is not symmetric in `(u, v)`.\n\n**`Set Node` arguments, three explicit per-set domain premises, walk-first universal.** `Set Node` matches `def_3_17`'s `IsSigmaBlockedGiven` carrier and `def_3_5`'s family-set carriers, admitting the LN's \"not necessarily disjoint, nor disjoint from `J`, nor non-empty\" permissiveness. The three named hypotheses `hA, hB, hC : · ⊆ ↑G.J ∪ ↑G.V` mirror \"$A, B, C \\subseteq J \\cup V$\" verbatim and close the silent-admission leak; only `hC` is consumed (threaded into `π.IsSigmaBlockedGiven C hC`), so each statement is prefixed with `set_option linter.unusedVariables false in`. The universal is `∀ {u v} (π : Walk G u v), …` with `{u v}` implicit (inferred from the walk's type, mirroring `def_3_16`'s binder shape); `Walk.nil` is in scope by construction, σ-open by emptiness of the position existential.\n\n**Named `def` for the negation, definitionally equal to `¬ IsISigmaSeparated`.** The LN's `\\nisPerp` is notation for the negation of `\\isPerp`, not a new concept. `G.IsNotISigmaSeparated … := ¬ G.IsISigmaSeparated …` carries the same three subset premises; unfolding holds by `rfl`, so `unfold` / `simp only` collapses to the negation with no classical bridge. The tex's \"$\\exists$ walk … not $C$-$\\sigma$-blocked\" reformulation is the De Morgan dual, available as a one-line lemma; a parallel positive-existential `def` would sever the definitional link.\n\n**`abbrev` for the `C = ∅` shorthand; `def` with explicit `hJ : G.J = ∅` for the σ-renames.** LN item 3 is pure notation: `abbrev IsISigmaSeparatedEmpty (G) (A B) (hA hB)` reduces eagerly to `G.IsISigmaSeparated A B ∅ hA hB (Set.empty_subset _)`; the third subset hypothesis is discharged inline. LN item 4 renames under a hypothesis: `def IsSigmaSeparated (G) (hJ) (A B C) (hA hB hC)` forwards to `G.IsISigmaSeparated …`, paired with `def IsNotSigmaSeparated` forwarding to `G.IsNotISigmaSeparated`. Under `hJ` the asymmetric `v ∈ J ∪ B` reduces to `v ∈ B` at consumer sites via `hJ` in scope, not via the body. `def` over `abbrev` keeps the σ-vs-iσ name and `hJ` visible in goal displays; `abbrev` would erase both at unrelated tactic steps. The premise is the bare equation `G.J = ∅`, not `(hDMG : G.IsDMG)`, so this row does not transitively depend on `def_3_7`. `IsNotSigmaSeparated`'s `hJ` is signature-mirror only — kept for σ/¬σ name-pairing with item 4.\n\n**Operator addition `[sigma_symmetry_claim_invokes_unstated_reversal_invariance]` is background.** The LN-faithful symmetry justification — walk reversal is an involution on the set of walks in $G$ and σ-blocking on internal nodes is stated invariantly under reversal — is treated as background per the canonical tex's \"Treatment of the trailing LN remark\". The symmetry claim itself is `claim_3_22` (`SigmaSeparationSymmetric`); no Lean obligation is derived here from the embedded `claimmark`. Its proof draws on the structural reversal invariance of `Walk` and `IsSigmaBlockedGiven` directly, transported across the flat `∀`-walk shape this def commits to."
}
